{"nodes":[
{"name":"Land Allocation"},
{"name":"Food"},
{"name":"Processing"},
{"name":"Feed"},
{"name":"Other"},
{"name":"Waste"},
{"name":"Cereal Production"},
{"name":"Starchy Roots Production"},
{"name":"Oil Crops Production"},
{"name":"Pulses Production"},
{"name":"Nuts Production"},
{"name":"Vegetables Production"},
{"name":"Fruits Production"},
{"name":"Sugar Crops Production"},
{"name":"Stimulants Production"},
{"name":"Spices Production"},
{"name":"Fibers Production"},
{"name":"Tobacco Production"},
{"name":"Rubber Production"},
{"name":"Fodder Production"},
{"name":"Cereal Yield"},
{"name":"Starchy Roots Yield"},
{"name":"Oil Crops Yield"},
{"name":"Pulses Yield"},
{"name":"Nuts Yield"},
{"name":"Vegetables Yield"},
{"name":"Fruits Yield"},
{"name":"Sugar Crops Yield"},
{"name":"Stimulants Yield"},
{"name":"Spices Yield"},
{"name":"Fibers Yield"},
{"name":"Tobacco Yield"},
{"name":"Rubber Yield"},
{"name":"Fodder Yield"},
{"name":"Vegetable Oils"},
{"name":"Oil Cakes"},
{"name":"Sugar"},
{"name":"Alcohol"}, 
{"name":"Open Range Land"}, 
{"name":"Meat Production"}, 
{"name":"Fats Production"}, 
{"name":"Hides and Skins Production"}, 
{"name":"Milk, Primary Production"}, 
{"name":"Eggs Production"}, 
{"name":"Honey Production"}, 
{"name":"Wool & Hair Production"},
{"name":"Silk Production"},
{"name":"Animals"},
{"name":"Food- Animal"},
{"name":"Processing- Animal"},
{"name":"Feed- Animal"},
{"name":"Other- Animal"},
{"name":"Waste- Animal"}, 
{"name":"Primary Imports"}, 
{"name":"Primary Exports"}, 
{"name":"Processing Imports"}, 
{"name":"Processing Exports"}
],

"links":[
{"source":0,"target":20,"value":863777.71},
{"source":0,"target":21,"value":87195.63},
{"source":0,"target":22,"value":253493.06},
{"source":0,"target":23,"value":29148.18},
{"source":0,"target":24,"value":8302.52},
{"source":0,"target":25,"value":227422.14},
{"source":0,"target":26,"value":121323.47},
{"source":0,"target":27,"value":18409.41},
{"source":0,"target":28,"value":15673.50},
{"source":0,"target":29,"value":2008.44},
{"source":0,"target":30,"value":1254.11},
{"source":0,"target":31,"value":13906.60},
{"source":0,"target":32,"value":5394.16},
{"source":0,"target":33,"value":33795.40},

{"source":20,"target":6,"value":468931},
{"source":21,"target":7,"value":177099},
{"source":22,"target":8,"value":59948},
{"source":23,"target":9,"value":5035},
{"source":24,"target":10,"value":3786},
{"source":25,"target":11,"value":590077},
{"source":26,"target":12,"value":146120},
{"source":27,"target":13,"value":130402},
{"source":28,"target":14,"value":1790},
{"source":29,"target":15,"value":1040},
{"source":30,"target":16,"value":6944.029},
{"source":31,"target":17,"value":3296.337},
{"source":32,"target":18,"value":750.852},
{"source":33,"target":19,"value":85885.1},

{"source":6,"target":1,"value":237207},
{"source":7,"target":1,"value":101570},
{"source":8,"target":1,"value":12194},
{"source":9,"target":1,"value":2472},
{"source":10,"target":1,"value":4062},
{"source":11,"target":1,"value":493083},
{"source":12,"target":1,"value":129664},
{"source":14,"target":1,"value":36},
{"source":15,"target":1,"value":2372},
{"source":16,"target":1,"value":615},

{"source":6,"target":2,"value":14968},
{"source":7,"target":2,"value":10574},
{"source":8,"target":2,"value":94402},
{"source":12,"target":2,"value":7121},
{"source":13,"target":2,"value":118757},
{"source":16,"target":2,"value":25},
{"source":17,"target":2,"value":-14.545},

{"source":6,"target":3,"value":193956},
{"source":7,"target":3,"value":69903},
{"source":8,"target":3,"value":11433},
{"source":9,"target":3,"value":2182},
{"source":11,"target":3,"value":37841},
{"source":13,"target":3,"value":11608},

{"source":6,"target":4,"value":38536},
{"source":7,"target":4,"value":6532},
{"source":8,"target":4,"value":712},
{"source":11,"target":4,"value":21},
{"source":12,"target":4,"value":35},
{"source":14,"target":4,"value":1},
{"source":16,"target":4,"value":11515.908},
{"source":17,"target":4,"value":3427.561},
{"source":18,"target":4,"value":4149.099},

{"source":6,"target":5,"value":20749},
{"source":7,"target":5,"value":9003},
{"source":8,"target":5,"value":2950},
{"source":9,"target":5,"value":179},
{"source":10,"target":5,"value":83},
{"source":11,"target":5,"value":51313},
{"source":12,"target":5,"value":13850},
{"source":14,"target":5,"value":49},
{"source":15,"target":5,"value":11},
{"source":17,"target":5,"value":4.26},

{"source":2,"target":34,"value":22300},
{"source":2,"target":35,"value":68381.384},
{"source":2,"target":36,"value":20966},
{"source":2,"target":37,"value":72246},

{"source":34,"target":1,"value":13801},
{"source":34,"target":4,"value":20021},
{"source":34,"target":5,"value":130},

{"source":35,"target":3,"value":70457.055},
{"source":35,"target":4,"value":5125.084},

{"source":36,"target":1,"value":15378},
{"source":36,"target":3,"value":2327.366},
{"source":36,"target":4,"value":2323865.678},
{"source":36,"target":5,"value":22.156},

{"source":37,"target":1,"value":70340},
{"source":37,"target":4,"value":3517},
{"source":37,"target":5,"value":57},

{"source":38,"target":19,"value":3600}, 
{"source":19,"target":3,"value":85885.1}, 

{"source":3,"target":47,"value":708214.3469},

{"source":47,"target":39,"value":89187},
{"source":47,"target":40,"value":4047},
{"source":47,"target":41,"value":2914.287},
{"source":47,"target":42,"value":51654},
{"source":47,"target":43,"value":31705},
{"source":47,"target":44,"value":470},
{"source":47,"target":45,"value":666.111},
{"source":47,"target":46,"value":487.806},

{"source":39,"target":48,"value":96101},
{"source":39,"target":49,"value":17},
{"source":39,"target":50,"value":52},
{"source":39,"target":51,"value":450},
{"source":39,"target":52,"value":111}, 

{"source":40,"target":48,"value":2963},
{"source":40,"target":50,"value":47},
{"source":40,"target":51,"value":1931},

{"source":41,"target":49,"value":-0.001},
{"source":41,"target":51,"value":4859.331}, 
{"source":41,"target":52,"value":26.327}, 

{"source":42,"target":48,"value":54934},
{"source":42,"target":49,"value":1},
{"source":42,"target":50,"value":2937},
{"source":42,"target":51,"value":365},
{"source":42,"target":52,"value":1541}, 

{"source":43,"target":48,"value":28902},
{"source":43,"target":51,"value":481},
{"source":43,"target":52,"value":1534}, 

{"source":44,"target":48,"value":545},
{"source":44,"target":49,"value":19},

{"source":45,"target":49,"value":417},

{"source":46,"target":49,"value":0.9},
{"source":46,"target":51,"value":482.12},

{"source":49,"target":48,"value":18.899}, 

{"source":53,"target":6,"value":52975},
{"source":53,"target":7,"value":24721},
{"source":53,"target":8,"value":64476},
{"source":53,"target":9,"value":1075},
{"source":53,"target":10,"value":818},
{"source":53,"target":11,"value":5967},
{"source":53,"target":12,"value":11539},
{"source":53,"target":13,"value":1},
{"source":53,"target":14,"value":1280},
{"source":53,"target":15,"value":164},
{"source":53,"target":16,"value":4653.847},
{"source":53,"target":17,"value":407.887},
{"source":53,"target":18,"value":3416.869}, 

{"source":53,"target":39,"value":10188},
{"source":53,"target":40,"value":949},
{"source":53,"target":41,"value":2312.155},
{"source":53,"target":42,"value":8471},
{"source":53,"target":43,"value":174},
{"source":53,"target":44,"value":49},
{"source":53,"target":45,"value":351.982},
{"source":53,"target":46,"value":3.542},

{"source":6,"target":54,"value":3314},
{"source":7,"target":54,"value":1109},
{"source":8,"target":54,"value":1056},
{"source":9,"target":54,"value":996},
{"source":10,"target":54,"value":534},
{"source":11,"target":54,"value":13787},
{"source":12,"target":54,"value":6985},
{"source":13,"target":54,"value":2},
{"source":14,"target":54,"value":670},
{"source":15,"target":54,"value":579},
{"source":16,"target":54,"value":57.687},
{"source":17,"target":54,"value":369.898},
{"source":18,"target":54,"value":18.622},

{"source":39,"target":54,"value":2569},
{"source":40,"target":54,"value":57},
{"source":41,"target":54,"value":325.479},
{"source":42,"target":54,"value":361},
{"source":43,"target":54,"value":111},
{"source":44,"target":54,"value":101},
{"source":45,"target":54,"value":28.978},
{"source":45,"target":54,"value":9.043},

{"source":55,"target":34,"value":11934},
{"source":55,"target":35,"value":7874.294},
{"source":55,"target":36,"value":8909.892},
{"source":55,"target":37,"value":2560},

{"source":34,"target":56,"value":330},
{"source":35,"target":56,"value":673.536},
{"source":36,"target":56,"value":2140.456},
{"source":37,"target":56,"value":881}


]}